arcade_imgui/__init__.py
arcade_imgui-0.4.0.dist-info/LICENSE
arcade_imgui-0.4.0.dist-info/WHEEL
arcade_imgui-0.4.0.dist-info/METADATA
arcade_imgui-0.4.0.dist-info/RECORD
