Metadata-Version: 2.1
Name: arcade-imgui
Version: 0.4.0
Summary: IMGUI integration for Python Arcade
Home-page: https://github.com/kfields/arcade-imgui
License: MIT
Keywords: arcade,game,gui
Author: Kurtis Fields
Author-email: kurtisfields@gmail.com
Requires-Python: >=3.8,<3.12
Classifier: Development Status :: 4 - Beta
Classifier: Intended Audience :: Developers
Classifier: License :: OSI Approved :: MIT License
Classifier: Operating System :: OS Independent
Classifier: Programming Language :: Python
Classifier: Programming Language :: Python :: 3
Classifier: Programming Language :: Python :: 3.10
Classifier: Programming Language :: Python :: 3.8
Classifier: Programming Language :: Python :: 3.9
Classifier: Topic :: Games/Entertainment :: Arcade
Classifier: Topic :: Software Development :: Libraries :: Python Modules
Classifier: Topic :: Software Development :: User Interfaces
Requires-Dist: arcade (>=2.6.16,<3.0.0)
Requires-Dist: imgui (>=1.4.1,<2.0.0)
Project-URL: Documentation, https://github.com/kfields/arcade-imgui
Project-URL: Repository, https://github.com/kfields/arcade-imgui
